.gitignore
LICENSE
README.md
setup.py
panda_example_django/__init__.py
panda_example_django/config.py
panda_example_django/urls.py
panda_example_django/views.py
panda_example_django.egg-info/PKG-INFO
panda_example_django.egg-info/SOURCES.txt
panda_example_django.egg-info/dependency_links.txt
panda_example_django.egg-info/requires.txt
panda_example_django.egg-info/top_level.txt
panda_example_django/static/panda_uploader/choose_file_button.png
panda_example_django/static/panda_uploader/jquery.panda-uploader.min.js
panda_example_django/static/panda_uploader/panda-uploader.css
panda_example_django/static/panda_uploader/progress_bg.gif
panda_example_django/static/panda_uploader/progress_fg.gif
panda_example_django/static/panda_uploader/swfobject.js
panda_example_django/static/panda_uploader/swfupload.swf
panda_example_django/templates/panda_example_django/index.html
panda_example_django/templates/panda_example_django/layout.html
panda_example_django/templates/panda_example_django/player.html