Metadata-Version: 1.0
Name: panda-example-django
Version: 1.1
Summary: An example of how to integrate Panda on your Django application
Home-page: http://github.com/newbamboo/panda_example_django
Author: New Bamboo
Author-email: info@new-bamboo.co.uk
License: MIT
Keywords: panda video encoding stream service example
Platform: UNKNOWN
Classifier: License :: OSI Approved :: MIT License
Classifier: Programming Language :: Python
Classifier: Development Status :: 4 - Beta
Classifier: Intended Audience :: Developers
Classifier: Topic :: Internet :: WWW/HTTP
